Workbook

Sheet Sheet1
B8: Monthly budget
B9: january-2022- june 2022
B10: House Payment | C10: 1200 | D10: 1200 | E10: 1200 | F10: 1200 | G10: 1200 | H10: 1200 | I10: =AVERAGE(C10:H10) -> 1200 | J10: =SUM(C10:H10) -> 7200
B11: Gasoline | C11: 50 | D11: 60 | E11: 55 | F11: 65 | G11: 62 | H11: 70 | I11: =AVERAGE(C11:H11) -> 60.333333 | J11: =SUM(C11:H11) -> 362
B12: Groceries | C12: 300 | D12: 320 | E12: 310 | F12: 305 | G12: 330 | H12: 315 | I12: =AVERAGE(C12:H12) -> 313.33333 | J12: =SUM(C12:H12) -> 1880
B13: Utilities | C13: 150 | D13: 145 | E13: 160 | F13: 155 | G13: 150 | H13: 148 | I13: =AVERAGE(C13:H13) -> 151.33333 | J13: =SUM(C13:H13) -> 908
B14: Insurance | C14: 200 | D14: 200 | E14: 200 | F14: 200 | G14: 200 | H14: 200 | I14: =AVERAGE(C14:H14) -> 200 | J14: =SUM(C14:H14) -> 1200
B15: Entertainment | C15: 100 | D15: 120 | E15: 90 | F15: 80 | G15: 110 | H15: 95 | I15: =AVERAGE(C15:H15) -> 99.166667 | J15: =SUM(C15:H15) -> 595
B16: Other | C16: 75 | D16: 60 | E16: 85 | F16: 70 | G16: 90 | H16: 65 | I16: =AVERAGE(C16:H16) -> 74.166667 | J16: =SUM(C16:H16) -> 445
B17: Monthly Expenses Total | C17: =SUM(C10:C16) -> 2075 | D17: =SUM(D10:D16) -> 2105 | E17: =SUM(E10:E16) -> 2100 | F17: =SUM(F10:F16) -> 2075 | G17: 2142 | H17: 2093
B19: Income | C19: 2000 | D19: 2100 | E19: 2700 | F19: 1900 | G19: 2500 | H19: 2900

Sheet Sheet2
B2: Category | C2: Total (Jan-Jun) | E2: Month | F2: Expenses (Monthly Total) | G2: Income
B3: House Payment | C3: =Sheet1!J10 -> 7200 | E3: January | F3: =Sheet1!C17 -> 2075 | G3: =Sheet1!C19 -> 2000
B4: Gasoline | C4: =Sheet1!J11 -> 362 | E4: February | F4: =Sheet1!D17 -> 2105 | G4: =Sheet1!D19 -> 2100
B5: Groceries | C5: =Sheet1!J12 -> 1880 | E5: March | F5: =Sheet1!E17 -> 2100 | G5: =Sheet1!E19 -> 2700
B6: Utilities | C6: =Sheet1!J13 -> 908 | E6: April | F6: =Sheet1!F17 -> 2075 | G6: =Sheet1!F19 -> 1900
B7: Insurance | C7: =Sheet1!J14 -> 1200 | E7: May | F7: =Sheet1!G17 -> 2142 | G7: =Sheet1!G19 -> 2500
B8: Entertainment | C8: =Sheet1!J15 -> 595 | E8: June | F8: =Sheet1!H17 -> 2093 | G8: =Sheet1!H19 -> 2900
B9: Other | C9: =Sheet1!J16 -> 445
B11: Chart Date: | C11: 46003
