Workbook

Sheet Budget
A13: Monthly Budget
A14: January 2022 – June 2022
A15: House Payment | B15: 1200 | C15: 1200 | D15: 1200 | E15: 1200 | F15: 1200 | G15: 1200 | H15: =AVERAGE(B15:G15) -> 1200 | I15: =SUM(B15:G15) -> 7200
A16: Gasoline | B16: 50 | C16: 60 | D16: 55 | E16: 65 | F16: 62 | G16: 70 | H16: =AVERAGE(B16:G16) -> 60.333333 | I16: =SUM(B16:G16) -> 362
A17: Groceries | B17: 300 | C17: 320 | D17: 310 | E17: 305 | F17: 330 | G17: 315 | H17: =AVERAGE(B17:G17) -> 313.33333 | I17: =SUM(B17:G17) -> 1880
A18: Utilities | B18: 150 | C18: 145 | D18: 160 | E18: 155 | F18: 150 | G18: 148 | H18: =AVERAGE(B18:G18) -> 151.33333 | I18: =SUM(B18:G18) -> 908
A19: Insurance | B19: 200 | C19: 200 | D19: 200 | E19: 200 | F19: 200 | G19: 200 | H19: =AVERAGE(B19:G19) -> 200 | I19: =SUM(B19:G19) -> 1200
A20: Entertainment | B20: 100 | C20: 120 | D20: 90 | E20: 80 | F20: 110 | G20: 95 | H20: =AVERAGE(B20:G20) -> 99.166667 | I20: =SUM(B20:G20) -> 595
A21: Other | B21: 75 | C21: 60 | D21: 85 | E21: 70 | F21: 90 | G21: 65 | H21: =AVERAGE(B21:G21) -> 74.166667 | I21: =SUM(B21:G21) -> 445
A22: Monthly Expenses Total | B22: =SUM(B15:B21) -> 2075 | C22: =SUM(C15:C21) -> 2105 | D22: =SUM(D15:D21) -> 2100 | E22: =SUM(E15:E21) -> 2075 | F22: =SUM(F15:F21) -> 2142 | G22: =SUM(G15:G21) -> 2093
A24: Income | B24: 2000 | C24: 2100 | D24: 2700 | E24: 1900 | F24: 2500 | G24: 2900

Sheet Charts
A1: Category | B1: Total (Jan-Jun) | D1: Month | E1: Expenses (Monthly Total) | F1: Income
A2: House Payment | B2: =Budget!I15 -> 7200 | D2: January | E2: =Budget!B22 -> 2075 | F2: =Budget!B24 -> 2000
A3: Gasoline | B3: =Budget!I16 -> 362 | D3: February | E3: =Budget!C22 -> 2105 | F3: =Budget!C24 -> 2100
A4: Groceries | B4: =Budget!I17 -> 1880 | D4: March | E4: =Budget!D22 -> 2100 | F4: =Budget!D24 -> 2700
A5: Utilities | B5: =Budget!I18 -> 908 | D5: April | E5: =Budget!E22 -> 2075 | F5: =Budget!E24 -> 1900
A6: Insurance | B6: =Budget!I19 -> 1200 | D6: May | E6: =Budget!F22 -> 2142 | F6: =Budget!F24 -> 2500
A7: Entertainment | B7: =Budget!I20 -> 595 | D7: June | E7: =Budget!G22 -> 2093 | F7: =Budget!G24 -> 2900
A8: Other | B8: =Budget!I21 -> 445
A11: Chart Date: | B11: December 12, 2025
